syssimpyplots/__init__.py
syssimpyplots/compare_kepler.py
syssimpyplots/compute_RVs.py
syssimpyplots/general.py
syssimpyplots/load_sims.py
syssimpyplots/plot_catalogs.py
syssimpyplots/plot_params.py
syssimpyplots/data/Clustered_P_R_split_stars_weights_ADmod_true_targs88912_evals100_all_pairs.txt
syssimpyplots/data/MRpredict_table_weights3025_R1001_Q1001.txt
syssimpyplots/data/q1_q17_dr25_gaia_berger_fgk_H2020_cleaned.csv
syssimpyplots/data/q1_q17_dr25_gaia_berger_fgk_H2020_koi_cleaned.csv
syssimpyplots/data/q1_q17_dr25_gaia_fgk_HFR2021a_cleaned.csv
syssimpyplots/data/q1_q17_dr25_gaia_fgk_HFR2021a_koi_cleaned.csv
syssimpyplots-1.1.0.dist-info/LICENSE
syssimpyplots-1.1.0.dist-info/METADATA
syssimpyplots-1.1.0.dist-info/WHEEL
syssimpyplots-1.1.0.dist-info/top_level.txt
syssimpyplots-1.1.0.dist-info/RECORD
