Metadata-Version: 2.1
Name: syssimpyplots
Version: 1.1.0
Summary: A Python codebase for loading, analyzing, and plotting catalogs from the SysSim Clustered Planetary System Models
Author-email: Matthias Yang He <mhe@nd.edu>
License: MIT License        
Project-URL: Homepage, https://syssimpyplots.readthedocs.io
Project-URL: Source, https://github.com/hematthi/SysSimPyPlots
Project-URL: Bug Tracker, https://github.com/hematthi/SysSimPyPlots/issues
Classifier: Programming Language :: Python :: 3
Classifier: License :: OSI Approved :: MIT License
Classifier: Operating System :: OS Independent
Classifier: Intended Audience :: Science/Research
Requires-Python: >=3.7
License-File: LICENSE
